{
  "number": "229",
  "lines": [
    {
      "text": "If Mind is not the master of sin, sickness, and death,",
      "flyout_text": null,
      "paragraph_start": true
    },
    {
      "text": "they are immortal, for it is already proved that mat-",
      "flyout_text": null,
      "paragraph_start": false
    },
    {
      "text": "ter has not destroyed them, but is their basis and",
      "flyout_text": null,
      "paragraph_start": false
    },
    {
      "text": "support.",
      "flyout_text": "No union of opposites",
      "paragraph_start": false
    },
    {
      "text": "We should hesitate to say that Jehovah sins or suffers;",
      "flyout_text": null,
      "paragraph_start": true
    },
    {
      "text": "but if sin and suffering are realities of being, whence did",
      "flyout_text": null,
      "paragraph_start": false
    },
    {
      "text": "they emanate? God made all that was made,",
      "flyout_text": null,
      "paragraph_start": false
    },
    {
      "text": "and Mind signifies God, - infinity, not finity.",
      "flyout_text": null,
      "paragraph_start": false
    },
    {
      "text": "Not far removed from infidelity is the belief which",
      "flyout_text": null,
      "paragraph_start": false
    },
    {
      "text": "unites such opposites as sickness and health, holiness",
      "flyout_text": null,
      "paragraph_start": false
    },
    {
      "text": "and unholiness, calls both the offspring of spirit, and",
      "flyout_text": null,
      "paragraph_start": false
    },
    {
      "text": "at the same time admits that Spirit is God, - vir-",
      "flyout_text": null,
      "paragraph_start": false
    },
    {
      "text": "tually declaring Him good in one instance and evil in",
      "flyout_text": null,
      "paragraph_start": false
    },
    {
      "text": "another.",
      "flyout_text": "Self-constituted law",
      "paragraph_start": false
    },
    {
      "text": "By universal consent, mortal belief has constituted",
      "flyout_text": null,
      "paragraph_start": true
    },
    {
      "text": "itself a law to bind mortals to sickness, sin, and death.",
      "flyout_text": null,
      "paragraph_start": false
    },
    {
      "text": "This customary belief is misnamed material",
      "flyout_text": null,
      "paragraph_start": false
    },
    {
      "text": "law, and the individual who upholds it is mis-",
      "flyout_text": null,
      "paragraph_start": false
    },
    {
      "text": "taken in theory and in practice. The so-called law of",
      "flyout_text": null,
      "paragraph_start": false
    },
    {
      "text": "mortal mind, conjectural and speculative, is made void",
      "flyout_text": null,
      "paragraph_start": false
    },
    {
      "text": "by the law of immortal Mind, and false law should be",
      "flyout_text": null,
      "paragraph_start": false
    },
    {
      "text": "trampled under foot.",
      "flyout_text": "Sickness from mortal mind",
      "paragraph_start": false
    },
    {
      "text": "If God causes man to be sick, sickness must be good,",
      "flyout_text": null,
      "paragraph_start": true
    },
    {
      "text": "and its opposite, health, must be evil, for all that He",
      "flyout_text": null,
      "paragraph_start": false
    },
    {
      "text": "makes is good and will stand forever. If the",
      "flyout_text": null,
      "paragraph_start": false
    },
    {
      "text": "transgression of God's law produces sickness, it",
      "flyout_text": null,
      "paragraph_start": false
    },
    {
      "text": "is right to be sick; and we cannot if we would, and should",
      "flyout_text": null,
      "paragraph_start": false
    },
    {
      "text": "not if we could, annul the decrees of wisdom. It is the",
      "flyout_text": null,
      "paragraph_start": false
    },
    {
      "text": "transgression of a belief of mortal mind, not of a law of",
      "flyout_text": null,
      "paragraph_start": false
    },
    {
      "text": "matter nor of divine Mind, which causes the belief of sick-",
      "flyout_text": null,
      "paragraph_start": false
    },
    {
      "text": "ness. The remedy is Truth, not matter, - the truth that",
      "flyout_text": null,
      "paragraph_start": false
    },
    {
      "text": "disease is _unreal_.",
      "flyout_text": null,
      "paragraph_start": false
    }
  ]
}