{"number":"251","lines":[{"text":"Error is not real, hence it is not more imperative","flyout_text":null,"paragraph_start":true},{"text":"as it hastens towards self-destruction. The so-called","flyout_text":null,"paragraph_start":false},{"text":"belief of mortal mind apparent as an abscess","flyout_text":null,"paragraph_start":false},{"text":"should not grow more painful before it suppu-","flyout_text":null,"paragraph_start":false},{"text":"rates neither should a fever become more severe before","flyout_text":null,"paragraph_start":false},{"text":"it ends.","flyout_text":"Illusion of death","paragraph_start":false},{"text":"Fright is so great at certain stages of mortal belief","flyout_text":null,"paragraph_start":true},{"text":"as to drive belief into new paths. In the illusion of","flyout_text":null,"paragraph_start":false},{"text":"death, mortals wake to the knowledge of two","flyout_text":null,"paragraph_start":false},{"text":"facts: (1) that they are not dead; (2) that","flyout_text":null,"paragraph_start":false},{"text":"they have but passed the portals of a new belief. Truth","flyout_text":null,"paragraph_start":false},{"text":"works out the nothingness of error in just these ways.","flyout_text":null,"paragraph_start":false},{"text":"Sickness, as well as sin, is an error that Christ, Truth,","flyout_text":null,"paragraph_start":false},{"text":"alone can destroy.","flyout_text":"Mortal mind's disappearance","paragraph_start":false},{"text":"We must learn how mankind govern the body, -","flyout_text":null,"paragraph_start":true},{"text":"whether through faith in hygiene, in drugs, or in will-","flyout_text":null,"paragraph_start":false},{"text":"power. We should learn whether they govern","flyout_text":null,"paragraph_start":false},{"text":"the body through a belief in the necessity of","flyout_text":null,"paragraph_start":false},{"text":"sickness and death, sin and pardon, or govern","flyout_text":null,"paragraph_start":false},{"text":"it from the higher understanding that the divine Mind","flyout_text":null,"paragraph_start":false},{"text":"makes perfect, acts upon the so-called human mind","flyout_text":null,"paragraph_start":false},{"text":"through truth, leads the human mind to relinquish all","flyout_text":null,"paragraph_start":false},{"text":"error, to find the divine Mind to be the only Mind,","flyout_text":null,"paragraph_start":false},{"text":"and the healer of sin, disease, death. This process of","flyout_text":null,"paragraph_start":false},{"text":"higher spiritual understanding improves mankind until","flyout_text":null,"paragraph_start":false},{"text":"error disappears, and nothing is left which deserves to","flyout_text":null,"paragraph_start":false},{"text":"perish or to be punished.","flyout_text":"Spiritual ignorance","paragraph_start":false},{"text":"Ignorance, like intentional wrong, is not Science.","flyout_text":null,"paragraph_start":true},{"text":"Ignorance must be seen and corrected before we can at-","flyout_text":null,"paragraph_start":false},{"text":"tain harmony. Inharmonious beliefs, which","flyout_text":null,"paragraph_start":false},{"text":"rob Mind, calling it matter, and deify their","flyout_text":null,"paragraph_start":false},{"text":"own notions, imprison themselves in what they create.","flyout_text":null,"paragraph_start":false}]}