{"number":"253","lines":[{"text":"likeness. He reflects the infinite understanding, for I am","flyout_text":null,"paragraph_start":false},{"text":"Infinity. The beauty of holiness, the perfection of being,","flyout_text":null,"paragraph_start":false},{"text":"imperishable glory, - all are Mine, for I am","flyout_text":null,"paragraph_start":false},{"text":"God. I give immortality to man, for I am","flyout_text":null,"paragraph_start":false},{"text":"Truth. I include and impart all bliss, for I am Love.","flyout_text":null,"paragraph_start":false},{"text":"I give life, without beginning and without end, for I am","flyout_text":null,"paragraph_start":false},{"text":"Life. I am supreme and give all, for I am Mind. I am","flyout_text":null,"paragraph_start":false},{"text":"the substance of all, because I AM THAT I AM.","flyout_text":"Heaven-bestowed prerogative","paragraph_start":false},{"text":"I hope, dear reader, I am leading you into the under-","flyout_text":null,"paragraph_start":true},{"text":"standing of your divine rights, your heaven-bestowed har-","flyout_text":null,"paragraph_start":false},{"text":"mony, - that, as you read, you see there is no","flyout_text":null,"paragraph_start":false},{"text":"cause (outside of erring, mortal, material sense","flyout_text":null,"paragraph_start":false},{"text":"which is not power) able to make you sick or","flyout_text":null,"paragraph_start":false},{"text":"sinful; and I hope that you are conquering this false sense.","flyout_text":null,"paragraph_start":false},{"text":"Knowing the falsity of so-called material sense, you can","flyout_text":null,"paragraph_start":false},{"text":"assert your prerogative to overcome the belief in sin, dis-","flyout_text":null,"paragraph_start":false},{"text":"ease, or death.","flyout_text":"Right endeavor possible","paragraph_start":false},{"text":"If you believe in and practise wrong knowingly, you","flyout_text":null,"paragraph_start":true},{"text":"can at once change your course and do right. Matter can","flyout_text":null,"paragraph_start":false},{"text":"make no opposition to right endeavors against","flyout_text":null,"paragraph_start":false},{"text":"sin or sickness, for matter is inert, mindless.","flyout_text":null,"paragraph_start":false},{"text":"Also, if you believe yourself diseased, you can","flyout_text":null,"paragraph_start":false},{"text":"alter this wrong belief and action without hindrance from","flyout_text":null,"paragraph_start":false},{"text":"the body.","flyout_text":null,"paragraph_start":false},{"text":"Do not believe in any supposed necessity for sin, dis-","flyout_text":null,"paragraph_start":true},{"text":"ease, or death, knowing (as you ought to know) that God","flyout_text":null,"paragraph_start":false},{"text":"never requires obedience to a so-called material law, for","flyout_text":null,"paragraph_start":false},{"text":"no such law exists. The belief in sin and death is de-","flyout_text":null,"paragraph_start":false},{"text":"stroyed by the law of God, which is the law of Life in-","flyout_text":null,"paragraph_start":false},{"text":"stead of death, of harmony instead of discord, of Spirit","flyout_text":null,"paragraph_start":false},{"text":"instead of the flesh.","flyout_text":"Patience and final perfection","paragraph_start":false},{"text":"The divine demand, \"Be ye therefore perfect,\" is sci-","flyout_text":null,"paragraph_start":true}]}