{"number":"29","lines":[{"text":"sufficient moral courage. Christians must take up arms","flyout_text":null,"paragraph_start":false},{"text":"against error at home and abroad. They must grapple","flyout_text":null,"paragraph_start":false},{"text":"with sin in themselves and in others, and","flyout_text":null,"paragraph_start":false},{"text":"continue this warfare until they have finished","flyout_text":null,"paragraph_start":false},{"text":"their course. If they keep the faith, they will have the","flyout_text":null,"paragraph_start":false},{"text":"crown of rejoicing.","flyout_text":null,"paragraph_start":false},{"text":"Christian experience teaches faith in the right and dis-","flyout_text":null,"paragraph_start":true},{"text":"belief in the wrong. It bids us work the more earnestly","flyout_text":null,"paragraph_start":false},{"text":"in times of persecution, because then our labor is more","flyout_text":null,"paragraph_start":false},{"text":"needed. Great is the reward of self-sacrifice, though we","flyout_text":null,"paragraph_start":false},{"text":"may never receive it in this world.","flyout_text":"The Fatherhood of God","paragraph_start":false},{"text":"There is a tradition that Publius Lentulus wrote to","flyout_text":null,"paragraph_start":true},{"text":"the authorities at Rome: \"The disciples of Jesus be-","flyout_text":null,"paragraph_start":false},{"text":"lieve him the Son of God.\" Those instructed","flyout_text":null,"paragraph_start":false},{"text":"in Christian Science have reached the glori-","flyout_text":null,"paragraph_start":false},{"text":"ous perception that God is the only author of man.","flyout_text":null,"paragraph_start":false},{"text":"The Virgin-mother conceived this idea of God, and","flyout_text":null,"paragraph_start":false},{"text":"gave to her ideal the name of Jesus - that is, Joshua,","flyout_text":null,"paragraph_start":false},{"text":"or Saviour.","flyout_text":"Spiritual conception","paragraph_start":false},{"text":"The illumination of Mary's spiritual sense put to","flyout_text":null,"paragraph_start":true},{"text":"silence material law and its order of generation, and","flyout_text":null,"paragraph_start":false},{"text":"brought forth her child by the revelation of","flyout_text":null,"paragraph_start":false},{"text":"Truth, demonstrating God as the Father of","flyout_text":null,"paragraph_start":false},{"text":"men. The Holy Ghost, or divine Spirit, overshadowed","flyout_text":null,"paragraph_start":false},{"text":"the pure sense of the Virgin-mother with the full recog-","flyout_text":null,"paragraph_start":false},{"text":"nition that being is Spirit. The Christ dwelt forever","flyout_text":null,"paragraph_start":false},{"text":"an idea in the bosom of God, the divine Principle of the","flyout_text":null,"paragraph_start":false},{"text":"man Jesus, and woman perceived this spiritual idea,","flyout_text":null,"paragraph_start":false},{"text":"though at first faintly developed.","flyout_text":null,"paragraph_start":false},{"text":"Man as the offspring of God, as the idea of Spirit,","flyout_text":null,"paragraph_start":true},{"text":"is the immortal evidence that Spirit is harmonious and","flyout_text":null,"paragraph_start":false},{"text":"man eternal. Jesus was the offspring of Mary's self-","flyout_text":null,"paragraph_start":false}]}