{"number":"53","lines":[{"text":"through Beelzebub,\" and is the \"friend of publicans and","flyout_text":null,"paragraph_start":false},{"text":"sinners.\" The latter accusation was true, but not in their","flyout_text":null,"paragraph_start":false},{"text":"meaning. Jesus was no ascetic. He did not fast as did","flyout_text":null,"paragraph_start":false},{"text":"the Baptist's disciples; yet there never lived a man so far","flyout_text":null,"paragraph_start":false},{"text":"removed from appetites and passions as the Nazarene.","flyout_text":null,"paragraph_start":false},{"text":"He rebuked sinners pointedly and unflinchingly, because","flyout_text":null,"paragraph_start":false},{"text":"he was their friend; hence the cup he drank.","flyout_text":"Reputation and character","paragraph_start":false},{"text":"The reputation of Jesus was the very opposite of his","flyout_text":null,"paragraph_start":true},{"text":"character. Why? Because the divine Principle and","flyout_text":null,"paragraph_start":false},{"text":"practice of Jesus were misunderstood. He","flyout_text":null,"paragraph_start":false},{"text":"was at work in divine Science. His words","flyout_text":null,"paragraph_start":false},{"text":"and works were unknown to the world because above","flyout_text":null,"paragraph_start":false},{"text":"and contrary to the world's religious sense. Mortals be-","flyout_text":null,"paragraph_start":false},{"text":"lieved in God as humanly mighty, rather than as divine,","flyout_text":null,"paragraph_start":false},{"text":"infinite Love.","flyout_text":"Inspiring discontent","paragraph_start":false},{"text":"The world could not interpret aright the discomfort","flyout_text":null,"paragraph_start":true},{"text":"which Jesus inspired and the spiritual blessings which","flyout_text":null,"paragraph_start":false},{"text":"might flow from such discomfort. Science","flyout_text":null,"paragraph_start":false},{"text":"shows the cause of the shock so often pro-","flyout_text":null,"paragraph_start":false},{"text":"duced by the truth, - namely, that this shock arises from","flyout_text":null,"paragraph_start":false},{"text":"the great distance between the individual and Truth.","flyout_text":null,"paragraph_start":false},{"text":"Like Peter, we should weep over the warning, instead of","flyout_text":null,"paragraph_start":false},{"text":"denying the truth or mocking the lifelong sacrifice which","flyout_text":null,"paragraph_start":false},{"text":"goodness makes for the destruction of evil.","flyout_text":"Bearing our sins","paragraph_start":false},{"text":"Jesus bore our sins in his body. He knew the","flyout_text":null,"paragraph_start":true},{"text":"mortal errors which constitute the material body, and","flyout_text":null,"paragraph_start":false},{"text":"could destroy those errors; but at the time","flyout_text":null,"paragraph_start":false},{"text":"when Jesus felt our infirmities, he had not","flyout_text":null,"paragraph_start":false},{"text":"conquered all the beliefs of the flesh or his sense of ma-","flyout_text":null,"paragraph_start":false},{"text":"terial life, nor had he risen to his final demonstration of","flyout_text":null,"paragraph_start":false},{"text":"spiritual power.","flyout_text":null,"paragraph_start":false},{"text":"Had he shared the sinful beliefs of others, he would","flyout_text":null,"paragraph_start":true}]}