{"number":"549","lines":[{"text":"division.\" This discovery is corroborative of the Science","flyout_text":null,"paragraph_start":false},{"text":"of Mind, for this discovery shows that the multiplication","flyout_text":null,"paragraph_start":false},{"text":"of certain animals takes place apart from sexual condi-","flyout_text":null,"paragraph_start":false},{"text":"tions. The supposition that life germinates in eggs and","flyout_text":null,"paragraph_start":false},{"text":"must decay after it has grown to maturity, if not before,","flyout_text":null,"paragraph_start":false},{"text":"is shown by divine metaphysics to be a mistake, - a","flyout_text":null,"paragraph_start":false},{"text":"blunder which will finally give place to higher theories","flyout_text":null,"paragraph_start":false},{"text":"and demonstrations.","flyout_text":"The three processes","paragraph_start":false},{"text":"Creatures of lower forms of organism are supposed","flyout_text":null,"paragraph_start":true},{"text":"to have, as classes, three different methods of reproduc-","flyout_text":null,"paragraph_start":false},{"text":"tion and to multiply their species sometimes","flyout_text":null,"paragraph_start":false},{"text":"through eggs, sometimes through buds, and","flyout_text":null,"paragraph_start":false},{"text":"sometimes through self-division. According to recent","flyout_text":null,"paragraph_start":false},{"text":"lore, successive generations do not begin with the _birth_ of","flyout_text":null,"paragraph_start":false},{"text":"new individuals, or personalities, but with the formation","flyout_text":null,"paragraph_start":false},{"text":"of the nucleus, or egg, from which one or more individu-","flyout_text":null,"paragraph_start":false},{"text":"alities subsequently emerge; and we must therefore look","flyout_text":null,"paragraph_start":false},{"text":"upon the simple ovum as the germ, the starting-point, of","flyout_text":null,"paragraph_start":false},{"text":"the most complicated corporeal structures, including those","flyout_text":null,"paragraph_start":false},{"text":"which we call human. Here these material researches","flyout_text":null,"paragraph_start":false},{"text":"culminate in such vague hypotheses as must necessarily","flyout_text":null,"paragraph_start":false},{"text":"attend false systems, which rely upon physics and are de-","flyout_text":null,"paragraph_start":false},{"text":"void of metaphysics.","flyout_text":"Deference to material law","paragraph_start":false},{"text":"In one instance a celebrated naturalist, Agassiz, dis-","flyout_text":null,"paragraph_start":true},{"text":"covers the pathway leading to divine Science, and beards","flyout_text":null,"paragraph_start":false},{"text":"the lion of materialism in its den. At that","flyout_text":null,"paragraph_start":false},{"text":"point, however, even this great observer mis-","flyout_text":null,"paragraph_start":false},{"text":"takes nature, forsakes Spirit as the divine origin of","flyout_text":null,"paragraph_start":false},{"text":"creative Truth, and allows matter and material law to","flyout_text":null,"paragraph_start":false},{"text":"usurp the prerogatives of omnipotence. He absolutely","flyout_text":null,"paragraph_start":false},{"text":"drops from his summit, coming down to a belief in the","flyout_text":null,"paragraph_start":false},{"text":"material origin of man, for he virtually affirms that","flyout_text":null,"paragraph_start":false}]}