{
  "number": "86",
  "lines": [
    {
      "text": "Jesus once asked, \"Who touched me?\" Supposing",
      "flyout_text": null,
      "paragraph_start": true
    },
    {
      "text": "this inquiry to be occasioned by physical contact alone,",
      "flyout_text": null,
      "paragraph_start": false
    },
    {
      "text": "his disciples answered, \"The multitude throng",
      "flyout_text": null,
      "paragraph_start": false
    },
    {
      "text": "thee.\" Jesus knew, as others did not, that",
      "flyout_text": null,
      "paragraph_start": false
    },
    {
      "text": "it was not matter, but mortal mind, whose touch called",
      "flyout_text": null,
      "paragraph_start": false
    },
    {
      "text": "for aid. Repeating his inquiry, he was answered by the",
      "flyout_text": null,
      "paragraph_start": false
    },
    {
      "text": "faith of a sick woman. His quick apprehension of this",
      "flyout_text": null,
      "paragraph_start": false
    },
    {
      "text": "mental call illustrated his spirituality. The disciples'",
      "flyout_text": null,
      "paragraph_start": false
    },
    {
      "text": "misconception of it uncovered their materiality. Jesus",
      "flyout_text": null,
      "paragraph_start": false
    },
    {
      "text": "possessed more spiritual susceptibility than the disciples.",
      "flyout_text": null,
      "paragraph_start": false
    },
    {
      "text": "Opposites come from contrary directions, and produce",
      "flyout_text": null,
      "paragraph_start": false
    },
    {
      "text": "unlike results.",
      "flyout_text": "Images of thought",
      "paragraph_start": false
    },
    {
      "text": "Mortals evolve images of thought. These may appear",
      "flyout_text": null,
      "paragraph_start": true
    },
    {
      "text": "to the ignorant to be apparitions; but they are myste-",
      "flyout_text": null,
      "paragraph_start": false
    },
    {
      "text": "rious only because it is unusual to see",
      "flyout_text": null,
      "paragraph_start": false
    },
    {
      "text": "thoughts, though we can always feel their",
      "flyout_text": null,
      "paragraph_start": false
    },
    {
      "text": "influence. Haunted houses, ghostly voices, unusual",
      "flyout_text": null,
      "paragraph_start": false
    },
    {
      "text": "noises, and apparitions brought out in dark seances",
      "flyout_text": null,
      "paragraph_start": false
    },
    {
      "text": "either involve feats by tricksters, or they are images and",
      "flyout_text": null,
      "paragraph_start": false
    },
    {
      "text": "sounds evolved involuntarily by mortal mind. Seeing",
      "flyout_text": null,
      "paragraph_start": false
    },
    {
      "text": "is no less a quality of physical sense than feeling. Then",
      "flyout_text": null,
      "paragraph_start": false
    },
    {
      "text": "why is it more difficult to see a thought than to feel one?",
      "flyout_text": null,
      "paragraph_start": false
    },
    {
      "text": "Education alone determines the difference. In reality",
      "flyout_text": null,
      "paragraph_start": false
    },
    {
      "text": "there is none.",
      "flyout_text": "Phenomena explained",
      "paragraph_start": false
    },
    {
      "text": "Portraits, landscape-paintings, fac-similes of penman-",
      "flyout_text": null,
      "paragraph_start": true
    },
    {
      "text": "ship, peculiarities of expression, recollected sentences,",
      "flyout_text": null,
      "paragraph_start": false
    },
    {
      "text": "can all be taken from pictorial thought and",
      "flyout_text": null,
      "paragraph_start": false
    },
    {
      "text": "memory as readily as from objects cognizable",
      "flyout_text": null,
      "paragraph_start": false
    },
    {
      "text": "by the senses. Mortal mind sees what it believes as",
      "flyout_text": null,
      "paragraph_start": false
    },
    {
      "text": "certainly as it believes what it sees. It feels, hears, and",
      "flyout_text": null,
      "paragraph_start": false
    },
    {
      "text": "sees its own thoughts. Pictures are mentally formed",
      "flyout_text": null,
      "paragraph_start": false
    },
    {
      "text": "before the artist can convey them to canvas. So is it",
      "flyout_text": null,
      "paragraph_start": false
    }
  ]
}