{
  "number": "x",
  "lines": [
    {
      "text": "may treasure the memorials of a child's growth, and",
      "flyout_text": null,
      "paragraph_start": false
    },
    {
      "text": "she would not have them changed.",
      "flyout_text": null,
      "paragraph_start": false
    },
    {
      "text": "The first edition of SCIENCE AND HEALTH was pub-",
      "flyout_text": null,
      "paragraph_start": true
    },
    {
      "text": "lished in 1875. Various books on mental healing have",
      "flyout_text": null,
      "paragraph_start": false
    },
    {
      "text": "since been issued, most of them incorrect in theory",
      "flyout_text": null,
      "paragraph_start": false
    },
    {
      "text": "and filled with plagiarisms from SCIENCE AND HEALTH.",
      "flyout_text": null,
      "paragraph_start": false
    },
    {
      "text": "They regard the human mind as a healing agent,",
      "flyout_text": null,
      "paragraph_start": false
    },
    {
      "text": "whereas this mind is not a factor in the Principle of",
      "flyout_text": null,
      "paragraph_start": false
    },
    {
      "text": "Christian Science. A few books, however, which are",
      "flyout_text": null,
      "paragraph_start": false
    },
    {
      "text": "based on this book, are useful.",
      "flyout_text": null,
      "paragraph_start": false
    },
    {
      "text": "The author has not compromised conscience to suit",
      "flyout_text": null,
      "paragraph_start": true
    },
    {
      "text": "the general drift of thought, but has bluntly and hon-",
      "flyout_text": null,
      "paragraph_start": false
    },
    {
      "text": "estly given the text of Truth. She has made no effort",
      "flyout_text": null,
      "paragraph_start": false
    },
    {
      "text": "to embellish, elaborate, or treat in full detail so in-",
      "flyout_text": null,
      "paragraph_start": false
    },
    {
      "text": "finite a theme. By thousands of well-authenticated",
      "flyout_text": null,
      "paragraph_start": false
    },
    {
      "text": "cases of healing, she and her students have proved the",
      "flyout_text": null,
      "paragraph_start": false
    },
    {
      "text": "worth of her teachings. These cases for the most part",
      "flyout_text": null,
      "paragraph_start": false
    },
    {
      "text": "have been abandoned as hopeless by regular medical",
      "flyout_text": null,
      "paragraph_start": false
    },
    {
      "text": "attendants. Few invalids will turn to God till all",
      "flyout_text": null,
      "paragraph_start": false
    },
    {
      "text": "physical supports have failed, because there is so little",
      "flyout_text": null,
      "paragraph_start": false
    },
    {
      "text": "faith in His disposition and power to heal disease.",
      "flyout_text": null,
      "paragraph_start": false
    },
    {
      "text": "The divine Principle of healing is proved in the",
      "flyout_text": null,
      "paragraph_start": true
    },
    {
      "text": "personal experience of any sincere seeker of Truth. Its",
      "flyout_text": null,
      "paragraph_start": false
    },
    {
      "text": "purpose is good, and its practice is safer and more po-",
      "flyout_text": null,
      "paragraph_start": false
    },
    {
      "text": "tent than that of any other sanitary method. The un-",
      "flyout_text": null,
      "paragraph_start": false
    },
    {
      "text": "biased Christian thought is soonest touched by Truth,",
      "flyout_text": null,
      "paragraph_start": false
    },
    {
      "text": "and convinced of it. Only those quarrel with her",
      "flyout_text": null,
      "paragraph_start": false
    },
    {
      "text": "method who do not understand her meaning, or dis-",
      "flyout_text": null,
      "paragraph_start": false
    },
    {
      "text": "cerning the truth, come not to the light lest their",
      "flyout_text": null,
      "paragraph_start": false
    },
    {
      "text": "works be reproved. No intellectual proficiency is req-",
      "flyout_text": null,
      "paragraph_start": false
    },
    {
      "text": "uisite in the learner, but sound morals are most de-",
      "flyout_text": null,
      "paragraph_start": false
    },
    {
      "text": "sirable.",
      "flyout_text": null,
      "paragraph_start": false
    }
  ]
}